afcli/__init__.py
afcli/__main__.py
afcli-0.1.12.dist-info/METADATA
afcli-0.1.12.dist-info/WHEEL
afcli-0.1.12.dist-info/entry_points.txt
afcli-0.1.12.dist-info/licenses/LICENSE
afcli-0.1.12.dist-info/RECORD
