Metadata-Version: 2.4
Name: afcli
Version: 0.1.12
Summary: A command-line utility for interacting with Apache Airflow REST API
Project-URL: Homepage, https://github.com/ouachitalabs/af
Project-URL: Documentation, https://github.com/ouachitalabs/af#readme
Project-URL: Repository, https://github.com/ouachitalabs/af
Project-URL: Issues, https://github.com/ouachitalabs/af/issues
Author-email: John McCrary <john@ouachitalabs.com>
License: MIT License
License-File: LICENSE
Keywords: airflow,cli,data-engineering,rest-api,workflow
Classifier: Development Status :: 4 - Beta
Classifier: Intended Audience :: Developers
Classifier: License :: OSI Approved :: MIT License
Classifier: Operating System :: OS Independent
Classifier: Programming Language :: Python :: 3
Classifier: Programming Language :: Python :: 3.10
Classifier: Programming Language :: Python :: 3.11
Classifier: Programming Language :: Python :: 3.12
Classifier: Topic :: Software Development :: Libraries :: Python Modules
Classifier: Topic :: System :: Systems Administration
Requires-Python: >=3.10
Requires-Dist: apache-airflow-client==2.9.1
Requires-Dist: colorama>=0.4.6
Requires-Dist: requests>=2.31.0
Requires-Dist: rich>=13.0.0
Provides-Extra: test
Requires-Dist: freezegun>=1.2.0; extra == 'test'
Requires-Dist: pytest-cov>=4.1.0; extra == 'test'
Requires-Dist: pytest-mock>=3.11.0; extra == 'test'
Requires-Dist: pytest>=7.4.0; extra == 'test'
Requires-Dist: responses>=0.23.0; extra == 'test'
